rest/__init__.py
rest/api.py
rest/endpoint.py
rest/exceptions.py
rest/filters.py
rest/utils.py
rest/backends/__init__.py
rest/backends/starlette.py
aio_rest-0.0.2.dist-info/LICENSE
aio_rest-0.0.2.dist-info/METADATA
aio_rest-0.0.2.dist-info/WHEEL
aio_rest-0.0.2.dist-info/top_level.txt
aio_rest-0.0.2.dist-info/RECORD
