Metadata-Version: 2.1
Name: aio-rest
Version: 0.0.2
Summary: REST Helpers for Asyncio projects
Home-page: UNKNOWN
Author: Kirill Klenov
Author-email: horneds@gmail.com
License: MIT
Keywords: api rest framework
Platform: UNKNOWN
Classifier: Development Status :: 5 - Production/Stable
Classifier: Intended Audience :: Developers
Classifier: License :: OSI Approved :: MIT License
Classifier: Topic :: Software Development :: Libraries
Classifier: Programming Language :: Python :: 3.4
Classifier: Programming Language :: Python :: 3.5
Classifier: Programming Language :: Python :: 3.6
Classifier: Programming Language :: Python :: 3.7
Classifier: Programming Language :: Python :: 3.8
